getbible/__init__.py
getbible/getbible.py
getbible/getbible_book_number.py
getbible/getbible_reference.py
getbible/getbible_reference_trie.py
getbible/trie_node.py
getbible/data/aleppo.json
getbible/data/almeida.json
getbible/data/aov.json
getbible/data/arabicsv.json
getbible/data/basque.json
getbible/data/bibelselskap.json
getbible/data/bkr.json
getbible/data/breton.json
getbible/data/cep.json
getbible/data/chamorro.json
getbible/data/cns.json
getbible/data/cnt.json
getbible/data/codex.json
getbible/data/coptic.json
getbible/data/cornilescu.json
getbible/data/croatia.json
getbible/data/cus.json
getbible/data/cut.json
getbible/data/danish.json
getbible/data/darby.json
getbible/data/easternarmenian.json
getbible/data/esperanto.json
getbible/data/estonian.json
getbible/data/finnish.json
getbible/data/giovanni.json
getbible/data/judson.json
getbible/data/karoli.json
getbible/data/kjv.json
getbible/data/korean.json
getbible/data/lithuanian.json
getbible/data/ls1910.json
getbible/data/maori.json
getbible/data/martin.json
getbible/data/moderngreek.json
getbible/data/modernhebrew.json
getbible/data/pyharaamattu1933.json
getbible/data/pyharaamattu1992.json
getbible/data/riveduta.json
getbible/data/rv1858.json
getbible/data/sahidic.json
getbible/data/sse.json
getbible/data/statenvertaling.json
getbible/data/swahili.json
getbible/data/swedish.json
getbible/data/synodal.json
getbible/data/tagalog.json
getbible/data/texusreceptus.json
getbible/data/thai.json
getbible/data/tischendorf.json
getbible/data/turkish.json
getbible/data/ukranian.json
getbible/data/valera.json
getbible/data/vietnamese.json
getbible/data/vulgate.json
getbible/data/westcotthort.json
getbible/data/westernarmenian.json
getbible/data/zhuromsky.json
getbible-1.1.2.dist-info/LICENSE
getbible-1.1.2.dist-info/METADATA
getbible-1.1.2.dist-info/WHEEL
getbible-1.1.2.dist-info/top_level.txt
getbible-1.1.2.dist-info/RECORD
