Metadata-Version: 2.1
Name: getbible
Version: 1.1.2
Summary: A Python package to retrieving Bible references with ease.
Home-page: https://git.vdm.dev/getBible/librarian
Author: Llewellyn van der Merwe
Author-email: getbible@vdm.io
Classifier: Programming Language :: Python :: 3
Classifier: License :: OSI Approved :: GNU General Public License v2 or later (GPLv2+)
Classifier: Operating System :: OS Independent
Requires-Python: >=3.7
License-File: LICENSE
Requires-Dist: requests ~=2.31.0
